{"ignoredPaths":[{"value":"versioneer.py"},{"value":"mtj_softtuner/_version.py"},{"value":"README.md"},{"value":"mtj_softtuner/serialization.py"},{"value":"install.sh"},{"value":".github/"},{"value":"codacy_config/"}],"defaultIgnores":[{"value":".*reveal\\.js"},{"value":".*libs/.*"},{"value":".*dist/.*"},{"value":".*docs?/.*"},{"value":".*vendor/.*"},{"value":".*jquery\\.js"},{"value":".*\\.[Dd]esigner\\.cs"},{"value":".*bootstrap\\.js"},{"value":".*external/.*"},{"value":".*select2(-resource|)?\\.js"},{"value":".*jquery-ui\\.js"},{"value":".*[\\.-]min\\.css"},{"value":".*bootstrap\\.css"},{"value":".*lodash\\.js"},{"value":".*typeahead\\.js"},{"value":".*font-awesome\\.css"},{"value":".*samples?/.*"},{"value":".*three\\.js"},{"value":".*third[_-]?[Pp]arty/.*"},{"value":".*-ace\\.js"},{"value":".*underscore\\.js"},{"value":".*bower_components/.*"},{"value":".*builds?/.*"},{"value":".*[\\.-]min\\.js"},{"value":".*node_modules/.*"},{"value":".*d3\\.js"},{"value":".*angular(-resource|)?\\.js"},{"value":".*chart\\.js"},{"value":".*releases?/.*"}],"projectExtensions":[],"toolConfiguration":[{"uuid":"547ff16b-d57c-4d75-8067-5ccf3ea88a00","isEnabled":false,"notEdited":true,"patterns":[{"internalId":"markdownlint_MD044","parameters":[]},{"internalId":"markdownlint_MD001","parameters":[]},{"internalId":"markdownlint_MD034","parameters":[]},{"internalId":"markdownlint_MD037","parameters":[]},{"internalId":"markdownlint_MD043","parameters":[]},{"internalId":"markdownlint_MD019","parameters":[]},{"internalId":"markdownlint_MD007","parameters":[]},{"internalId":"markdownlint_MD003","parameters":[]},{"internalId":"markdownlint_MD009","parameters":[]},{"internalId":"markdownlint_MD014","parameters":[]},{"internalId":"markdownlint_MD040","parameters":[]},{"internalId":"markdownlint_MD027","parameters":[]},{"internalId":"markdownlint_MD021","parameters":[]},{"internalId":"markdownlint_MD041","parameters":[]},{"internalId":"markdownlint_MD048","parameters":[]},{"internalId":"markdownlint_MD011","parameters":[]},{"internalId":"markdownlint_MD023","parameters":[]},{"internalId":"markdownlint_MD047","parameters":[]},{"internalId":"markdownlint_MD038","parameters":[]},{"internalId":"markdownlint_MD032","parameters":[]},{"internalId":"markdownlint_MD010","parameters":[]},{"internalId":"markdownlint_MD046","parameters":[]},{"internalId":"markdownlint_MD035","parameters":[]},{"internalId":"markdownlint_MD028","parameters":[]},{"internalId":"markdownlint_MD004","parameters":[]},{"internalId":"markdownlint_MD033","parameters":[]},{"internalId":"markdownlint_MD012","parameters":[]},{"internalId":"markdownlint_MD030","parameters":[]},{"internalId":"markdownlint_MD042","parameters":[]},{"internalId":"markdownlint_MD025","parameters":[]},{"internalId":"markdownlint_MD026","parameters":[]},{"internalId":"markdownlint_MD024","parameters":[]},{"internalId":"markdownlint_MD031","parameters":[]},{"internalId":"markdownlint_MD029","parameters":[]},{"internalId":"markdownlint_MD002","parameters":[]},{"internalId":"markdownlint_MD005","parameters":[]},{"internalId":"markdownlint_MD020","parameters":[]},{"internalId":"markdownlint_MD013","parameters":[]},{"internalId":"markdownlint_MD036","parameters":[]},{"internalId":"markdownlint_MD022","parameters":[]},{"internalId":"markdownlint_MD045","parameters":[]},{"internalId":"markdownlint_MD006","parameters":[]},{"internalId":"markdownlint_MD039","parameters":[]},{"internalId":"markdownlint_MD018","parameters":[]}]},{"uuid":"4f94ee55-6b76-4765-8f38-9ebb3920762b","isEnabled":true,"notEdited":true,"patterns":[{"internalId":"jackson_parse-error","parameters":[]},{"internalId":"jackson_duplicate-keys","parameters":[]}]},{"uuid":"233f8aac-4fb6-4193-8a17-e64515bea152","isEnabled":true,"notEdited":false,"patterns":[{"internalId":"shellcheck_SC2091","parameters":[]},{"internalId":"shellcheck_SC2029","parameters":[]},{"internalId":"shellcheck_SC2006","parameters":[]},{"internalId":"shellcheck_SC2034","parameters":[]},{"internalId":"shellcheck_SC2003","parameters":[]},{"internalId":"shellcheck_SC2092","parameters":[]},{"internalId":"shellcheck_SC2015","parameters":[]},{"internalId":"shellcheck_SC2016","parameters":[]},{"internalId":"shellcheck_SC2024","parameters":[]},{"internalId":"shellcheck_SC2223","parameters":[]},{"internalId":"shellcheck_SC2031","parameters":[]},{"internalId":"shellcheck_SC2002","parameters":[]},{"internalId":"shellcheck_SC2028","parameters":[]},{"internalId":"shellcheck_SC2148","parameters":[]},{"internalId":"shellcheck_SC2033","parameters":[]},{"internalId":"shellcheck_SC2022","parameters":[]},{"internalId":"shellcheck_SC2025","parameters":[]},{"internalId":"shellcheck_SC2086","parameters":[]},{"internalId":"shellcheck_SC2001","parameters":[]},{"internalId":"shellcheck_SC2035","parameters":[]},{"internalId":"shellcheck_SC2027","parameters":[]},{"internalId":"shellcheck_SC2156","parameters":[]},{"internalId":"shellcheck_SC2036","parameters":[]},{"internalId":"shellcheck_SC2026","parameters":[]},{"internalId":"shellcheck_SC2020","parameters":[]},{"internalId":"shellcheck_SC2004","parameters":[]}]},{"uuid":"31677b6d-4ae0-4f56-8041-606a8d7a8e61","isEnabled":false,"notEdited":false,"patterns":[{"internalId":"PyLintPython3_E0712","parameters":[]},{"internalId":"PyLintPython3_W0711","parameters":[]},{"internalId":"PyLintPython3_E1123","parameters":[]},{"internalId":"PyLintPython3_E0100","parameters":[]},{"internalId":"PyLintPython3_W0612","parameters":[]},{"internalId":"PyLintPython3_W0105","parameters":[]},{"internalId":"PyLintPython3_W0222","parameters":[]},{"internalId":"PyLintPython3_E1102","parameters":[]},{"internalId":"PyLintPython3_E0110","parameters":[]},{"internalId":"PyLintPython3_E0604","parameters":[]},{"internalId":"PyLintPython3_W0623","parameters":[]},{"internalId":"PyLintPython3_E1303","parameters":[]},{"internalId":"PyLintPython3_W0611","parameters":[]},{"internalId":"PyLintPython3_E0202","parameters":[]},{"internalId":"PyLintPython3_W1306","parameters":[]},{"internalId":"PyLintPython3_C0201","parameters":[]},{"internalId":"PyLintPython3_E1205","parameters":[]},{"internalId":"PyLintPython3_E0112","parameters":[]},{"internalId":"PyLintPython3_W0404","parameters":[]},{"internalId":"PyLintPython3_E1120","parameters":[]},{"internalId":"PyLintPython3_E0710","parameters":[]},{"internalId":"PyLintPython3_W1303","parameters":[]},{"internalId":"PyLintPython3_E1304","parameters":[]},{"internalId":"PyLintPython3_E0703","parameters":[]},{"internalId":"PyLintPython3_C0303","parameters":[]},{"internalId":"PyLintPython3_R0203","parameters":[]},{"internalId":"PyLintPython3_W0120","parameters":[]},{"internalId":"PyLintPython3_E0240","parameters":[]},{"internalId":"PyLintPython3_E0103","parameters":[]},{"internalId":"PyLintPython3_E1111","parameters":[]},{"internalId":"PyLintPython3_R0201","parameters":[]},{"internalId":"PyLintPython3_E0711","parameters":[]},{"internalId":"PyLintPython3_E0116","parameters":[]},{"internalId":"PyLintPython3_E1300","parameters":[]},{"internalId":"PyLintPython3_E1200","parameters":[]},{"internalId":"PyLintPython3_W0122","parameters":[]},{"internalId":"PyLintPython3_W0102","parameters":[]},{"internalId":"PyLintPython3_E0104","parameters":[]},{"internalId":"PyLintPython3_W1307","parameters":[]},{"internalId":"PyLintPython3_W0221","parameters":[]},{"internalId":"PyLintPython3_W0602","parameters":[]},{"internalId":"PyLintPython3_E0701","parameters":[]},{"internalId":"PyLintPython3_E0117","parameters":[]},{"internalId":"PyLintPython3_W1302","parameters":[]},{"internalId":"PyLintPython3_E1306","parameters":[]},{"internalId":"PyLintPython3_E0107","parameters":[]},{"internalId":"PyLintPython3_E0115","parameters":[]},{"internalId":"PyLintPython3_E0601","parameters":[]},{"internalId":"PyLintPython3_E0702","parameters":[]},{"internalId":"PyLintPython3_E0704","parameters":[]},{"internalId":"PyLintPython3_E0203","parameters":[]},{"internalId":"PyLintPython3_W0124","parameters":[]},{"internalId":"PyLintPython3_E1003","parameters":[]},{"internalId":"PyLintPython3_W0150","parameters":[]},{"internalId":"PyLintPython3_E1201","parameters":[]},{"internalId":"PyLintPython3_E1301","parameters":[]},{"internalId":"PyLintPython3_E1206","parameters":[]},{"internalId":"PyLintPython3_W0107","parameters":[]},{"internalId":"PyLintPython3_W1300","parameters":[]},{"internalId":"PyLintPython3_E1124","parameters":[]},{"internalId":"PyLintPython3_W0604","parameters":[]},{"internalId":"PyLintPython3_W0104","parameters":[]},{"internalId":"PyLintPython3_E0106","parameters":[]},{"internalId":"PyLintPython3_E0113","parameters":[]},{"internalId":"PyLintPython3_E0108","parameters":[]},{"internalId":"PyLintPython3_W0622","parameters":[]},{"internalId":"PyLintPython3_E1132","parameters":[]},{"internalId":"PyLintPython3_E0101","parameters":[]},{"internalId":"PyLintPython3_E0102","parameters":[]},{"internalId":"PyLintPython3_W0109","parameters":[]},{"internalId":"PyLintPython3_W0702","parameters":[]},{"internalId":"PyLintPython3_W0108","parameters":[]},{"internalId":"PyLintPython3_E1302","parameters":[]},{"internalId":"PyLintPython3_E1126","parameters":[]},{"internalId":"PyLintPython3_E0239","parameters":[]},{"internalId":"PyLintPython3_W0199","parameters":[]},{"internalId":"PyLintPython3_W0601","parameters":[]},{"internalId":"PyLintPython3_E0238","parameters":[]},{"internalId":"PyLintPython3_W0233","parameters":[]},{"internalId":"PyLintPython3_C0200","parameters":[]},{"internalId":"PyLintPython3_E0211","parameters":[]},{"internalId":"PyLintPython3_W1305","parameters":[]},{"internalId":"PyLintPython3_W0123","parameters":[]},{"internalId":"PyLintPython3_E0114","parameters":[]},{"internalId":"PyLintPython3_E0236","parameters":[]},{"internalId":"PyLintPython3_W0705","parameters":[]},{"internalId":"PyLintPython3_W0101","parameters":[]},{"internalId":"PyLintPython3_E0301","parameters":[]},{"internalId":"PyLintPython3_E0105","parameters":[]},{"internalId":"PyLintPython3_E1125","parameters":[]},{"internalId":"PyLintPython3_E1121","parameters":[]},{"internalId":"PyLintPython3_E1127","parameters":[]},{"internalId":"PyLintPython3_C0123","parameters":[]},{"internalId":"PyLintPython3_W0410","parameters":[]},{"internalId":"PyLintPython3_R0202","parameters":[]},{"internalId":"PyLintPython3_W0106","parameters":[]},{"internalId":"PyLintPython3_E1305","parameters":[]},{"internalId":"PyLintPython3_E0302","parameters":[]},{"internalId":"PyLintPython3_W1301","parameters":[]},{"internalId":"PyLintPython3_E0603","parameters":[]},{"internalId":"PyLintPython3_E0241","parameters":[]}]},{"uuid":"34225275-f79e-4b85-8126-c7512c987c0d","isEnabled":true,"notEdited":false,"patterns":[{"internalId":"PyLint_W1306","parameters":[]},{"internalId":"PyLint_E0107","parameters":[]},{"internalId":"PyLint_E0101","parameters":[]},{"internalId":"PyLint_W0612","parameters":[]},{"internalId":"PyLint_W1305","parameters":[]},{"internalId":"PyLint_W1302","parameters":[]},{"internalId":"PyLint_E0601","parameters":[]},{"internalId":"PyLint_E0241","parameters":[]},{"internalId":"PyLint_E0239","parameters":[]},{"internalId":"PyLint_E0211","parameters":[]},{"internalId":"PyLint_W0233","parameters":[]},{"internalId":"PyLint_E0604","parameters":[]},{"internalId":"PyLint_W0109","parameters":[]},{"internalId":"PyLint_W0705","parameters":[]},{"internalId":"PyLint_E0711","parameters":[]},{"internalId":"PyLint_E1003","parameters":[]},{"internalId":"PyLint_E1305","parameters":[]},{"internalId":"PyLint_W0623","parameters":[]},{"internalId":"PyLint_W0199","parameters":[]},{"internalId":"PyLint_E1200","parameters":[]},{"internalId":"PyLint_E1304","parameters":[]},{"internalId":"PyLint_E0701","parameters":[]},{"internalId":"PyLint_C0123","parameters":[]},{"internalId":"PyLint_C0303","parameters":[]},{"internalId":"PyLint_W0108","parameters":[]},{"internalId":"PyLint_W0123","parameters":[]},{"internalId":"PyLint_E1302","parameters":[]},{"internalId":"PyLint_E0103","parameters":[]},{"internalId":"PyLint_E1111","parameters":[]},{"internalId":"PyLint_E0203","parameters":[]},{"internalId":"PyLint_W0102","parameters":[]},{"internalId":"PyLint_E0114","parameters":[]},{"internalId":"PyLint_E0106","parameters":[]},{"internalId":"PyLint_E0240","parameters":[]},{"internalId":"PyLint_W1303","parameters":[]},{"internalId":"PyLint_E0702","parameters":[]},{"internalId":"PyLint_W0611","parameters":[]},{"internalId":"PyLint_E1102","parameters":[]},{"internalId":"PyLint_W0122","parameters":[]},{"internalId":"PyLint_E1301","parameters":[]},{"internalId":"PyLint_E0603","parameters":[]},{"internalId":"PyLint_E1121","parameters":[]},{"internalId":"PyLint_W0604","parameters":[]},{"internalId":"PyLint_R0202","parameters":[]},{"internalId":"PyLint_E1127","parameters":[]},{"internalId":"PyLint_E0113","parameters":[]},{"internalId":"PyLint_W0222","parameters":[]},{"internalId":"PyLint_E1125","parameters":[]},{"internalId":"PyLint_W0622","parameters":[]},{"internalId":"PyLint_W0107","parameters":[]},{"internalId":"PyLint_E1132","parameters":[]},{"internalId":"PyLint_W0404","parameters":[]},{"internalId":"PyLint_W0124","parameters":[]},{"internalId":"PyLint_E0302","parameters":[]},{"internalId":"PyLint_E1206","parameters":[]},{"internalId":"PyLint_E0301","parameters":[]},{"internalId":"PyLint_W1301","parameters":[]},{"internalId":"PyLint_W0221","parameters":[]},{"internalId":"PyLint_E1205","parameters":[]},{"internalId":"PyLint_E1124","parameters":[]},{"internalId":"PyLint_E1303","parameters":[]},{"internalId":"PyLint_R0203","parameters":[]},{"internalId":"PyLint_E1300","parameters":[]},{"internalId":"PyLint_E0100","parameters":[]},{"internalId":"PyLint_W0601","parameters":[]},{"internalId":"PyLint_E1201","parameters":[]},{"internalId":"PyLint_W0410","parameters":[]},{"internalId":"PyLint_E0116","parameters":[]},{"internalId":"PyLint_W0106","parameters":[]},{"internalId":"PyLint_E0202","parameters":[]},{"internalId":"PyLint_W0602","parameters":[]},{"internalId":"PyLint_E1126","parameters":[]},{"internalId":"PyLint_E0112","parameters":[]},{"internalId":"PyLint_E0703","parameters":[]},{"internalId":"PyLint_C0200","parameters":[]},{"internalId":"PyLint_W0702","parameters":[]},{"internalId":"PyLint_W1300","parameters":[]},{"internalId":"PyLint_E1120","parameters":[]},{"internalId":"PyLint_W0105","parameters":[]},{"internalId":"PyLint_E0115","parameters":[]},{"internalId":"PyLint_E0236","parameters":[]},{"internalId":"PyLint_E0712","parameters":[]},{"internalId":"PyLint_E0110","parameters":[]},{"internalId":"PyLint_W1307","parameters":[]},{"internalId":"PyLint_W0110","parameters":[]},{"internalId":"PyLint_E0104","parameters":[]},{"internalId":"PyLint_E0704","parameters":[]},{"internalId":"PyLint_W0711","parameters":[]},{"internalId":"PyLint_C1001","parameters":[]},{"internalId":"PyLint_W0101","parameters":[]},{"internalId":"PyLint_E0102","parameters":[]},{"internalId":"PyLint_R0201","parameters":[]},{"internalId":"PyLint_E0105","parameters":[]},{"internalId":"PyLint_E1306","parameters":[]},{"internalId":"PyLint_E0108","parameters":[]},{"internalId":"PyLint_E1123","parameters":[]},{"internalId":"PyLint_W0120","parameters":[]},{"internalId":"PyLint_E0710","parameters":[]},{"internalId":"PyLint_E0117","parameters":[]},{"internalId":"PyLint_W0150","parameters":[]},{"internalId":"PyLint_E0238","parameters":[]}]},{"uuid":"f1eec388-0526-4c6c-954e-9b20b51bd9e7","isEnabled":true,"notEdited":false,"patterns":[{"internalId":"remark-lint-no-inline-padding","parameters":[]},{"internalId":"remark-lint-checkbox-character-style","parameters":[]},{"internalId":"remark-lint-definition-case","parameters":[]},{"internalId":"remark-lint-no-file-name-articles","parameters":[]},{"internalId":"remark-lint-strong-marker","parameters":[]},{"internalId":"remark-lint-no-file-name-outer-dashes","parameters":[]},{"internalId":"remark-lint-fenced-code-marker","parameters":[]},{"internalId":"remark-lint-heading-style","parameters":[]},{"internalId":"remark-lint-no-shell-dollars","parameters":[]},{"internalId":"remark-lint-ordered-list-marker-style","parameters":[]},{"internalId":"remark-lint-no-multiple-toplevel-headings","parameters":[]},{"internalId":"remark-lint-definition-spacing","parameters":[]},{"internalId":"remark-lint-list-item-spacing","parameters":[]},{"internalId":"remark-lint-table-pipes","parameters":[]},{"internalId":"remark-lint-no-duplicate-definitions","parameters":[]},{"internalId":"remark-lint-no-auto-link-without-protocol","parameters":[]},{"internalId":"remark-lint-final-definition","parameters":[]},{"internalId":"remark-lint-code-block-style","parameters":[]},{"internalId":"remark-lint-list-item-bullet-indent","parameters":[]},{"internalId":"remark-lint-no-emphasis-as-heading","parameters":[]},{"internalId":"remark-lint-emphasis-marker","parameters":[]},{"internalId":"remark-lint-table-cell-padding","parameters":[]},{"internalId":"remark-lint-no-heading-content-indent","parameters":[]},{"internalId":"remark-lint-blockquote-indentation","parameters":[]},{"internalId":"remark-lint-fenced-code-flag","parameters":[]},{"internalId":"remark-lint-no-undefined-references","parameters":[]},{"internalId":"remark-lint-no-table-indentation","parameters":[]},{"internalId":"remark-lint-link-title-style","parameters":[]},{"internalId":"remark-lint-table-pipe-alignment","parameters":[]},{"internalId":"remark-lint-no-heading-like-paragraph","parameters":[]},{"internalId":"remark-lint-no-shortcut-reference-link","parameters":[]},{"internalId":"remark-lint-no-blockquote-without-marker","parameters":[]},{"internalId":"remark-lint-no-literal-urls","parameters":[]},{"internalId":"remark-lint-no-duplicate-headings","parameters":[]},{"internalId":"remark-lint-no-heading-punctuation","parameters":[]},{"internalId":"remark-lint-list-item-indent","parameters":[]},{"internalId":"remark-lint-no-consecutive-blank-lines","parameters":[]},{"internalId":"remark-lint-no-shortcut-reference-image","parameters":[]},{"internalId":"remark-lint-ordered-list-marker-value","parameters":[]},{"internalId":"remark-lint-list-item-content-indent","parameters":[]},{"internalId":"remark-lint-unordered-list-marker-style","parameters":[]},{"internalId":"remark-lint-no-file-name-irregular-characters","parameters":[]},{"internalId":"remark-lint-rule-style","parameters":[]},{"internalId":"remark-lint-no-unused-definitions","parameters":[]}]},{"uuid":"fb60ff64-3d91-11ec-9bbc-0242ac130002","isEnabled":false,"notEdited":true,"patterns":[{"internalId":"spectral_typed-enum","parameters":[]},{"internalId":"spectral_asyncapi-info-description","parameters":[]},{"internalId":"spectral_operation-success-response","parameters":[]},{"internalId":"spectral_oas3-valid-media-example","parameters":[]},{"internalId":"spectral_asyncapi-operation-operationId","parameters":[]},{"internalId":"spectral_oas2-schema","parameters":[]},{"internalId":"spectral_asyncapi-channel-no-trailing-slash","parameters":[]},{"internalId":"spectral_no-$ref-siblings","parameters":[]},{"internalId":"spectral_oas3-operation-security-defined","parameters":[]},{"internalId":"spectral_asyncapi-channel-no-empty-parameter","parameters":[]},{"internalId":"spectral_oas2-valid-schema-example","parameters":[]},{"internalId":"spectral_oas3-valid-schema-example","parameters":[]},{"internalId":"spectral_asyncapi-tags","parameters":[]},{"internalId":"spectral_operation-description","parameters":[]},{"internalId":"spectral_asyncapi-channel-no-query-nor-fragment","parameters":[]},{"internalId":"spectral_oas2-api-host","parameters":[]},{"internalId":"spectral_asyncapi-schema-examples","parameters":[]},{"internalId":"spectral_oas3-schema","parameters":[]},{"internalId":"spectral_oas3-examples-value-or-externalValue","parameters":[]},{"internalId":"spectral_info-contact","parameters":[]},{"internalId":"spectral_asyncapi-schema-default","parameters":[]},{"internalId":"spectral_asyncapi-servers","parameters":[]},{"internalId":"spectral_oas2-unused-definition","parameters":[]},{"internalId":"spectral_oas2-oneOf","parameters":[]},{"internalId":"spectral_operation-tags","parameters":[]},{"internalId":"spectral_asyncapi-operation-description","parameters":[]},{"internalId":"spectral_no-script-tags-in-markdown","parameters":[]},{"internalId":"spectral_path-not-include-query","parameters":[]},{"internalId":"spectral_asyncapi-unused-components-schema","parameters":[]},{"internalId":"spectral_oas3-server-trailing-slash","parameters":[]},{"internalId":"spectral_info-description","parameters":[]},{"internalId":"spectral_asyncapi-headers-schema-type-object","parameters":[]},{"internalId":"spectral_duplicated-entry-in-enum","parameters":[]},{"internalId":"spectral_asyncapi-payload-default","parameters":[]},{"internalId":"spectral_operation-operationId","parameters":[]},{"internalId":"spectral_asyncapi-payload-examples","parameters":[]},{"internalId":"spectral_oas2-operation-security-defined","parameters":[]},{"internalId":"spectral_asyncapi-info-contact","parameters":[]},{"internalId":"spectral_asyncapi-payload","parameters":[]},{"internalId":"spectral_asyncapi-schema","parameters":[]},{"internalId":"spectral_oas2-host-trailing-slash","parameters":[]},{"internalId":"spectral_oas2-api-schemes","parameters":[]},{"internalId":"spectral_asyncapi-info-license","parameters":[]},{"internalId":"spectral_oas2-operation-formData-consume-check","parameters":[]},{"internalId":"spectral_operation-operationId-valid-in-url","parameters":[]},{"internalId":"spectral_oas3-unused-component","parameters":[]},{"internalId":"spectral_operation-operationId-unique","parameters":[]},{"internalId":"spectral_path-params","parameters":[]},{"internalId":"spectral_path-declarations-must-exist","parameters":[]},{"internalId":"spectral_path-keys-no-trailing-slash","parameters":[]},{"internalId":"spectral_oas2-anyOf","parameters":[]},{"internalId":"spectral_asyncapi-server-no-empty-variable","parameters":[]},{"internalId":"spectral_asyncapi-payload-unsupported-schemaFormat","parameters":[]},{"internalId":"spectral_oas2-valid-media-example","parameters":[]},{"internalId":"spectral_no-eval-in-markdown","parameters":[]},{"internalId":"spectral_asyncapi-info-contact-properties","parameters":[]},{"internalId":"spectral_operation-parameters","parameters":[]},{"internalId":"spectral_asyncapi-server-no-trailing-slash","parameters":[]},{"internalId":"spectral_operation-tag-defined","parameters":[]},{"internalId":"spectral_oas3-api-servers","parameters":[]}]},{"uuid":"89b6fc6a-9137-4cf3-8b9f-dcc3bedfa738","isEnabled":true,"notEdited":false,"patterns":[{"internalId":"Bandit_B411","parameters":[]},{"internalId":"Bandit_B502","parameters":[]},{"internalId":"Bandit_B405","parameters":[]},{"internalId":"Bandit_B308","parameters":[]},{"internalId":"Bandit_B312","parameters":[]},{"internalId":"Bandit_B413","parameters":[]},{"internalId":"Bandit_B703","parameters":[]},{"internalId":"Bandit_B109","parameters":[]},{"internalId":"Bandit_B301","parameters":[]},{"internalId":"Bandit_B504","parameters":[]},{"internalId":"Bandit_B609","parameters":[]},{"internalId":"Bandit_B325","parameters":[]},{"internalId":"Bandit_B107","parameters":[]},{"internalId":"Bandit_B111","parameters":[]},{"internalId":"Bandit_B102","parameters":[]},{"internalId":"Bandit_B321","parameters":[]},{"internalId":"Bandit_B603","parameters":[]},{"internalId":"Bandit_B104","parameters":[]},{"internalId":"Bandit_B401","parameters":[]},{"internalId":"Bandit_B404","parameters":[]},{"internalId":"Bandit_B306","parameters":[]},{"internalId":"Bandit_B606","parameters":[]},{"internalId":"Bandit_B602","parameters":[]},{"internalId":"Bandit_B311","parameters":[]},{"internalId":"Bandit_B601","parameters":[]},{"internalId":"Bandit_B701","parameters":[]},{"internalId":"Bandit_B608","parameters":[]},{"internalId":"Bandit_B702","parameters":[]},{"internalId":"Bandit_B604","parameters":[]},{"internalId":"Bandit_B314","parameters":[]},{"internalId":"Bandit_B317","parameters":[]},{"internalId":"Bandit_B409","parameters":[]},{"internalId":"Bandit_B201","parameters":[]},{"internalId":"Bandit_B112","parameters":[]},{"internalId":"Bandit_B503","parameters":[]},{"internalId":"Bandit_B507","parameters":[]},{"internalId":"Bandit_B316","parameters":[]},{"internalId":"Bandit_B305","parameters":[]},{"internalId":"Bandit_B318","parameters":[]},{"internalId":"Bandit_B605","parameters":[]},{"internalId":"Bandit_B319","parameters":[]},{"internalId":"Bandit_B407","parameters":[]},{"internalId":"Bandit_B320","parameters":[]},{"internalId":"Bandit_B304","parameters":[]},{"internalId":"Bandit_B313","parameters":[]},{"internalId":"Bandit_B302","parameters":[]},{"internalId":"Bandit_B303","parameters":[]},{"internalId":"Bandit_B402","parameters":[]},{"internalId":"Bandit_B408","parameters":[]},{"internalId":"Bandit_B105","parameters":[]},{"internalId":"Bandit_B110","parameters":[]},{"internalId":"Bandit_B501","parameters":[]},{"internalId":"Bandit_B103","parameters":[]},{"internalId":"Bandit_B414","parameters":[]},{"internalId":"Bandit_B410","parameters":[]},{"internalId":"Bandit_B323","parameters":[]},{"internalId":"Bandit_B315","parameters":[]},{"internalId":"Bandit_B406","parameters":[]},{"internalId":"Bandit_B307","parameters":[]},{"internalId":"Bandit_B309","parameters":[]},{"internalId":"Bandit_B607","parameters":[]},{"internalId":"Bandit_B610","parameters":[]},{"internalId":"Bandit_B322","parameters":[]},{"internalId":"Bandit_B611","parameters":[]},{"internalId":"Bandit_B505","parameters":[]},{"internalId":"Bandit_B506","parameters":[]},{"internalId":"Bandit_B403","parameters":[]},{"internalId":"Bandit_B310","parameters":[]},{"internalId":"Bandit_B108","parameters":[]}]},{"uuid":"25673894-eac1-4941-87a6-81f1abd5c321","isEnabled":true,"notEdited":false,"patterns":[{"internalId":"Prospector_dodgy","parameters":[]},{"internalId":"Prospector_pydocstyle","parameters":[]},{"internalId":"Prospector_pep257","parameters":[]},{"internalId":"Prospector_mccabe","parameters":[]}]},{"uuid":"13af9d89-1ce5-4fec-a168-765c3e7b26b3","isEnabled":false,"notEdited":false,"patterns":[{"internalId":"Checkov_CKV_AZURE_33","parameters":[]},{"internalId":"Checkov_CKV_AWS_28","parameters":[]},{"internalId":"Checkov_CKV_AWS_14","parameters":[]},{"internalId":"Checkov_CKV_AWS_11","parameters":[]},{"internalId":"Checkov_CKV_K8S_7","parameters":[]},{"internalId":"Checkov_CKV_AWS_20","parameters":[]},{"internalId":"Checkov_CKV_AZURE_31","parameters":[]},{"internalId":"Checkov_CKV_AWS_99","parameters":[]},{"internalId":"Checkov_CKV_AWS_48","parameters":[]},{"internalId":"Checkov_CKV_K8S_28","parameters":[]},{"internalId":"Checkov_CKV_AZURE_47","parameters":[]},{"internalId":"Checkov_CKV_GCP_17","parameters":[]},{"internalId":"Checkov_CKV_AWS_64","parameters":[]},{"internalId":"Checkov_CKV_AWS_94","parameters":[]},{"internalId":"Checkov_CKV_AWS_34","parameters":[]},{"internalId":"Checkov_CKV_AWS_10","parameters":[]},{"internalId":"Checkov_CKV_AZURE_11","parameters":[]},{"internalId":"Checkov_CKV_AWS_42","parameters":[]},{"internalId":"Checkov_CKV_K8S_32","parameters":[]},{"internalId":"Checkov_CKV_AWS_19","parameters":[]},{"internalId":"Checkov_CKV_AZURE_41","parameters":[]},{"internalId":"Checkov_CKV_AWS_51","parameters":[]},{"internalId":"Checkov_CKV_GCP_7","parameters":[]},{"internalId":"Checkov_CKV_AWS_49","parameters":[]},{"internalId":"Checkov_CKV_AWS_79","parameters":[]},{"internalId":"Checkov_CKV_AZURE_14","parameters":[]},{"internalId":"Checkov_CKV_AWS_25","parameters":[]},{"internalId":"Checkov_CKV_GCP_16","parameters":[]},{"internalId":"Checkov_CKV_GCP_37","parameters":[]},{"internalId":"Checkov_CKV_AZURE_4","parameters":[]},{"internalId":"Checkov_CKV_AZURE_23","parameters":[]},{"internalId":"Checkov_CKV_AZURE_7","parameters":[]},{"internalId":"Checkov_CKV_AWS_97","parameters":[]},{"internalId":"Checkov_CKV_GCP_50","parameters":[]},{"internalId":"Checkov_CKV_AZURE_43","parameters":[]},{"internalId":"Checkov_CKV_AZURE_28","parameters":[]},{"internalId":"Checkov_CKV_K8S_30","parameters":[]},{"internalId":"Checkov_CKV_AWS_86","parameters":[]},{"internalId":"Checkov_CKV_GCP_42","parameters":[]},{"internalId":"Checkov_CKV_K8S_10","parameters":[]},{"internalId":"Checkov_CKV_GCP_39","parameters":[]},{"internalId":"Checkov_CKV_AZURE_26","parameters":[]},{"internalId":"Checkov_CKV_AWS_58","parameters":[]},{"internalId":"Checkov_CKV_GCP_1","parameters":[]},{"internalId":"Checkov_CKV_K8S_37","parameters":[]},{"internalId":"Checkov_CKV_K8S_4","parameters":[]},{"internalId":"Checkov_CKV_AWS_105","parameters":[]},{"internalId":"Checkov_CKV_AWS_55","parameters":[]},{"internalId":"Checkov_CKV_GCP_3","parameters":[]},{"internalId":"Checkov_CKV_AWS_96","parameters":[]},{"internalId":"Checkov_CKV_AWS_5","parameters":[]},{"internalId":"Checkov_CKV_GCP_14","parameters":[]},{"internalId":"Checkov_CKV_AWS_23","parameters":[]},{"internalId":"Checkov_CKV_AWS_35","parameters":[]},{"internalId":"Checkov_CKV_AZURE_9","parameters":[]},{"internalId":"Checkov_CKV_AWS_3","parameters":[]},{"internalId":"Checkov_CKV_AWS_75","parameters":[]},{"internalId":"Checkov_CKV_GCP_29","parameters":[]},{"internalId":"Checkov_CKV_AWS_76","parameters":[]},{"internalId":"Checkov_CKV_GCP_45","parameters":[]},{"internalId":"Checkov_CKV_AWS_80","parameters":[]},{"internalId":"Checkov_CKV_AWS_47","parameters":[]},{"internalId":"Checkov_CKV_K8S_31","parameters":[]},{"internalId":"Checkov_CKV_K8S_25","parameters":[]},{"internalId":"Checkov_CKV_GCP_52","parameters":[]},{"internalId":"Checkov_CKV_AWS_69","parameters":[]},{"internalId":"Checkov_CKV_AWS_98","parameters":[]},{"internalId":"Checkov_CKV_K8S_41","parameters":[]},{"internalId":"Checkov_CKV_AZURE_37","parameters":[]},{"internalId":"Checkov_CKV_AZURE_49","parameters":[]},{"internalId":"Checkov_CKV_AWS_45","parameters":[]},{"internalId":"Checkov_CKV_K8S_33","parameters":[]},{"internalId":"Checkov_CKV_AWS_95","parameters":[]},{"internalId":"Checkov_CKV_AWS_54","parameters":[]},{"internalId":"Checkov_CKV_AWS_72","parameters":[]},{"internalId":"Checkov_CKV_AZURE_24","parameters":[]},{"internalId":"Checkov_CKV_AWS_30","parameters":[]},{"internalId":"Checkov_CKV_AWS_89","parameters":[]},{"internalId":"Checkov_CKV_GCP_48","parameters":[]},{"internalId":"Checkov_CKV_AWS_27","parameters":[]},{"internalId":"Checkov_CKV_K8S_3","parameters":[]},{"internalId":"Checkov_CKV_GCP_49","parameters":[]},{"internalId":"Checkov_CKV_K8S_9","parameters":[]},{"internalId":"Checkov_CKV_AWS_2","parameters":[]},{"internalId":"Checkov_CKV_AWS_103","parameters":[]},{"internalId":"Checkov_CKV_AWS_43","parameters":[]},{"internalId":"Checkov_CKV_AZURE_48","parameters":[]},{"internalId":"Checkov_CKV_K8S_17","parameters":[]},{"internalId":"Checkov_CKV_GCP_53","parameters":[]},{"internalId":"Checkov_CKV_GCP_25","parameters":[]},{"internalId":"Checkov_CKV_AZURE_34","parameters":[]},{"internalId":"Checkov_CKV_AWS_40","parameters":[]},{"internalId":"Checkov_CKV_K8S_19","parameters":[]},{"internalId":"Checkov_CKV_K8S_20","parameters":[]},{"internalId":"Checkov_CKV_AWS_32","parameters":[]},{"internalId":"Checkov_CKV_AWS_8","parameters":[]},{"internalId":"Checkov_CKV_AWS_17","parameters":[]},{"internalId":"Checkov_CKV_AWS_12","parameters":[]},{"internalId":"Checkov_CKV_AWS_1","parameters":[]},{"internalId":"Checkov_CKV_AZURE_52","parameters":[]},{"internalId":"Checkov_CKV_AWS_83","parameters":[]},{"internalId":"Checkov_CKV_GCP_34","parameters":[]},{"internalId":"Checkov_CKV_K8S_29","parameters":[]},{"internalId":"Checkov_CKV_AZURE_38","parameters":[]},{"internalId":"Checkov_CKV_GCP_23","parameters":[]},{"internalId":"Checkov_CKV_GCP_35","parameters":[]},{"internalId":"Checkov_CKV_AWS_38","parameters":[]},{"internalId":"Checkov_CKV_AWS_59","parameters":[]},{"internalId":"Checkov_CKV_AZURE_27","parameters":[]},{"internalId":"Checkov_CKV_AZURE_17","parameters":[]},{"internalId":"Checkov_CKV_AWS_91","parameters":[]},{"internalId":"Checkov_CKV_K8S_14","parameters":[]},{"internalId":"Checkov_CKV_K8S_40","parameters":[]},{"internalId":"Checkov_CKV_GCP_19","parameters":[]},{"internalId":"Checkov_CKV_GCP_55","parameters":[]},{"internalId":"Checkov_CKV_K8S_5","parameters":[]},{"internalId":"Checkov_CKV_AWS_70","parameters":[]},{"internalId":"Checkov_CKV_AWS_90","parameters":[]},{"internalId":"Checkov_CKV_K8S_2","parameters":[]},{"internalId":"Checkov_CKV_GCP_8","parameters":[]},{"internalId":"Checkov_CKV_AWS_101","parameters":[]},{"internalId":"Checkov_CKV_AZURE_13","parameters":[]},{"internalId":"Checkov_CKV_GCP_11","parameters":[]},{"internalId":"Checkov_CKV_AWS_26","parameters":[]},{"internalId":"Checkov_CKV_AZURE_53","parameters":[]},{"internalId":"Checkov_CKV_AWS_102","parameters":[]},{"internalId":"Checkov_CKV_GCP_31","parameters":[]},{"internalId":"Checkov_CKV_AWS_81","parameters":[]},{"internalId":"Checkov_CKV_AZURE_25","parameters":[]},{"internalId":"Checkov_CKV_K8S_16","parameters":[]},{"internalId":"Checkov_CKV_GCP_47","parameters":[]},{"internalId":"Checkov_CKV_AZURE_50","parameters":[]},{"internalId":"Checkov_CKV_GCP_33","parameters":[]},{"internalId":"Checkov_CKV_AWS_88","parameters":[]},{"internalId":"Checkov_CKV_AWS_15","parameters":[]},{"internalId":"Checkov_CKV_AWS_67","parameters":[]},{"internalId":"Checkov_CKV_AWS_18","parameters":[]},{"internalId":"Checkov_CKV_LIN_2","parameters":[]},{"internalId":"Checkov_CKV_AZURE_12","parameters":[]},{"internalId":"Checkov_CKV_GCP_57","parameters":[]},{"internalId":"Checkov_CKV_K8S_35","parameters":[]},{"internalId":"Checkov_CKV_K8S_18","parameters":[]},{"internalId":"Checkov_CKV_GCP_59","parameters":[]},{"internalId":"Checkov_CKV_AZURE_2","parameters":[]},{"internalId":"Checkov_CKV_AZURE_29","parameters":[]},{"internalId":"Checkov_CKV_AZURE_54","parameters":[]},{"internalId":"Checkov_CKV_AWS_100","parameters":[]},{"internalId":"Checkov_CKV_GIT_1","parameters":[]},{"internalId":"Checkov_CKV_GCP_44","parameters":[]},{"internalId":"Checkov_CKV_AWS_106","parameters":[]},{"internalId":"Checkov_CKV_AZURE_1","parameters":[]},{"internalId":"Checkov_CKV_AWS_71","parameters":[]},{"internalId":"Checkov_CKV_GCP_56","parameters":[]},{"internalId":"Checkov_CKV_AWS_60","parameters":[]},{"internalId":"Checkov_CKV_AZURE_5","parameters":[]},{"internalId":"Checkov_CKV_K8S_12","parameters":[]},{"internalId":"Checkov_CKV_GCP_46","parameters":[]},{"internalId":"Checkov_CKV_AWS_31","parameters":[]},{"internalId":"Checkov_CKV_AWS_92","parameters":[]},{"internalId":"Checkov_CKV_AWS_6","parameters":[]},{"internalId":"Checkov_CKV_AZURE_36","parameters":[]},{"internalId":"Checkov_CKV_GCP_43","parameters":[]},{"internalId":"Checkov_CKV_GCP_18","parameters":[]},{"internalId":"Checkov_CKV_AZURE_6","parameters":[]},{"internalId":"Checkov_CKV_K8S_13","parameters":[]},{"internalId":"Checkov_CKV_AZURE_39","parameters":[]},{"internalId":"Checkov_CKV_AZURE_30","parameters":[]},{"internalId":"Checkov_CKV_GCP_60","parameters":[]},{"internalId":"Checkov_CKV_K8S_38","parameters":[]},{"internalId":"Checkov_CKV_AWS_29","parameters":[]},{"internalId":"Checkov_CKV_K8S_27","parameters":[]},{"internalId":"Checkov_CKV_AZURE_8","parameters":[]},{"internalId":"Checkov_CKV_K8S_1","parameters":[]},{"internalId":"Checkov_CKV_AZURE_21","parameters":[]},{"internalId":"Checkov_CKV_AWS_66","parameters":[]},{"internalId":"Checkov_CKV_K8S_44","parameters":[]},{"internalId":"Checkov_CKV_AWS_46","parameters":[]},{"internalId":"Checkov_CKV_AWS_82","parameters":[]},{"internalId":"Checkov_CKV_K8S_8","parameters":[]},{"internalId":"Checkov_CKV_AWS_77","parameters":[]},{"internalId":"Checkov_CKV_AWS_21","parameters":[]},{"internalId":"Checkov_CKV_AZURE_46","parameters":[]},{"internalId":"Checkov_CKV_AWS_41","parameters":[]},{"internalId":"Checkov_CKV_GCP_54","parameters":[]},{"internalId":"Checkov_CKV_GCP_32","parameters":[]},{"internalId":"Checkov_CKV_GCP_21","parameters":[]},{"internalId":"Checkov_CKV_LIN_1","parameters":[]},{"internalId":"Checkov_CKV_GCP_6","parameters":[]},{"internalId":"Checkov_CKV_AWS_78","parameters":[]},{"internalId":"Checkov_CKV_AWS_24","parameters":[]},{"internalId":"Checkov_CKV_AZURE_22","parameters":[]},{"internalId":"Checkov_CKV_AWS_53","parameters":[]},{"internalId":"Checkov_CKV_AZURE_10","parameters":[]},{"internalId":"Checkov_CKV_GCP_24","parameters":[]},{"internalId":"Checkov_CKV_K8S_43","parameters":[]},{"internalId":"Checkov_CKV_GCP_30","parameters":[]},{"internalId":"Checkov_CKV_GCP_12","parameters":[]},{"internalId":"Checkov_CKV_AWS_65","parameters":[]},{"internalId":"Checkov_CKV_AWS_22","parameters":[]},{"internalId":"Checkov_CKV_AZURE_18","parameters":[]},{"internalId":"Checkov_CKV_AWS_37","parameters":[]},{"internalId":"Checkov_CKV_AWS_84","parameters":[]},{"internalId":"Checkov_CKV_K8S_42","parameters":[]},{"internalId":"Checkov_CKV_AZURE_16","parameters":[]},{"internalId":"Checkov_CKV_AZURE_35","parameters":[]},{"internalId":"Checkov_CKV_AZURE_19","parameters":[]},{"internalId":"Checkov_CKV_AZURE_40","parameters":[]},{"internalId":"Checkov_CKV_GCP_4","parameters":[]},{"internalId":"Checkov_CKV_K8S_24","parameters":[]},{"internalId":"Checkov_CKV_AZURE_44","parameters":[]},{"internalId":"Checkov_CKV_GCP_51","parameters":[]},{"internalId":"Checkov_CKV_AWS_68","parameters":[]},{"internalId":"Checkov_CKV_AZURE_42","parameters":[]},{"internalId":"Checkov_CKV_AZURE_20","parameters":[]},{"internalId":"Checkov_CKV_GCP_13","parameters":[]},{"internalId":"Checkov_CKV_GCP_20","parameters":[]},{"internalId":"Checkov_CKV_K8S_45","parameters":[]},{"internalId":"Checkov_CKV_K8S_11","parameters":[]},{"internalId":"Checkov_CKV_AWS_9","parameters":[]},{"internalId":"Checkov_CKV_GCP_10","parameters":[]},{"internalId":"Checkov_CKV_K8S_22","parameters":[]},{"internalId":"Checkov_CKV_AWS_61","parameters":[]},{"internalId":"Checkov_CKV_GCP_9","parameters":[]},{"internalId":"Checkov_CKV_AZURE_32","parameters":[]},{"internalId":"Checkov_CKV_AWS_44","parameters":[]},{"internalId":"Checkov_CKV_AZURE_15","parameters":[]},{"internalId":"Checkov_CKV_GCP_63","parameters":[]},{"internalId":"Checkov_CKV_AWS_56","parameters":[]},{"internalId":"Checkov_CKV_AWS_74","parameters":[]},{"internalId":"Checkov_CKV_GCP_22","parameters":[]},{"internalId":"Checkov_CKV_AWS_73","parameters":[]},{"internalId":"Checkov_CKV_GCP_26","parameters":[]},{"internalId":"Checkov_CKV_K8S_6","parameters":[]},{"internalId":"Checkov_CKV_K8S_21","parameters":[]},{"internalId":"Checkov_CKV_AZURE_3","parameters":[]},{"internalId":"Checkov_CKV_K8S_36","parameters":[]},{"internalId":"Checkov_CKV_K8S_26","parameters":[]},{"internalId":"Checkov_CKV_AWS_16","parameters":[]},{"internalId":"Checkov_CKV_K8S_15","parameters":[]},{"internalId":"Checkov_CKV_K8S_39","parameters":[]},{"internalId":"Checkov_CKV_K8S_34","parameters":[]},{"internalId":"Checkov_CKV_AWS_87","parameters":[]},{"internalId":"Checkov_CKV_AWS_36","parameters":[]},{"internalId":"Checkov_CKV_AWS_13","parameters":[]},{"internalId":"Checkov_CKV_K8S_23","parameters":[]},{"internalId":"Checkov_CKV_AWS_7","parameters":[]},{"internalId":"Checkov_CKV_AWS_57","parameters":[]},{"internalId":"Checkov_CKV_GCP_27","parameters":[]},{"internalId":"Checkov_CKV_AWS_39","parameters":[]},{"internalId":"Checkov_CKV_GCP_62","parameters":[]},{"internalId":"Checkov_CKV_GCP_28","parameters":[]},{"internalId":"Checkov_CKV_AWS_85","parameters":[]},{"internalId":"Checkov_CKV_AWS_63","parameters":[]},{"internalId":"Checkov_CKV_GCP_38","parameters":[]},{"internalId":"Checkov_CKV_AWS_62","parameters":[]},{"internalId":"Checkov_CKV_GCP_36","parameters":[]},{"internalId":"Checkov_CKV_AWS_33","parameters":[]},{"internalId":"Checkov_CKV_GCP_2","parameters":[]},{"internalId":"Checkov_CKV_GCP_41","parameters":[]},{"internalId":"Checkov_CKV_AWS_93","parameters":[]},{"internalId":"Checkov_CKV_AZURE_45","parameters":[]},{"internalId":"Checkov_CKV_GCP_58","parameters":[]},{"internalId":"Checkov_CKV_AWS_50","parameters":[]},{"internalId":"Checkov_CKV_GCP_15","parameters":[]},{"internalId":"Checkov_CKV_AWS_104","parameters":[]},{"internalId":"Checkov_CKV_GCP_40","parameters":[]}]}]}
